tests/__init__.py
tests/test_preprocess.py
text_preprocess_sanitizer/__init__.py
text_preprocess_sanitizer/language_models.py
text_preprocess_sanitizer/preprocess.py
text_sanitization_suite-0.3.dist-info/METADATA
text_sanitization_suite-0.3.dist-info/WHEEL
text_sanitization_suite-0.3.dist-info/top_level.txt
text_sanitization_suite-0.3.dist-info/RECORD
