Metadata-Version: 2.1
Name: text-sanitization-suite
Version: 0.3
Summary: Text Sanitization Suite is a robust Python package designed for personas who work in Data Science Domain i.e Data Scientists, Data Analysts, AI Engineers, Machine learning professionals to efficiently clean and prepare text data. 
Author: Gaurav Singh
Author-email: gauravdsmailbox@gmail.com
Classifier: Intended Audience :: Developers
Classifier: Topic :: Text Processing :: Linguistic
Classifier: License :: OSI Approved :: MIT License
Classifier: Operating System :: OS Independent
Classifier: Programming Language :: Python :: 3
Classifier: Programming Language :: Python :: 3.6
Classifier: Programming Language :: Python :: 3.7
Classifier: Programming Language :: Python :: 3.8
Classifier: Programming Language :: Python :: 3.9
Classifier: Programming Language :: Python :: 3.10
Classifier: Programming Language :: Python :: 3.11
Classifier: Programming Language :: Python :: 3.12
Requires-Python: >=3.6
Requires-Dist: pandas
Requires-Dist: nltk
Requires-Dist: spacy
Requires-Dist: langdetect
